{
   "alternate" : [],
   "grid" : "MONTH",
   "name" : "Aurealis",
   "years" : {
      "1990" : [
         {
            "date" : "Apr",
            "issue" : "1",
            "status" : "BOUND"
         },
         {
            "date" : "Oct",
            "issue" : "2",
            "status" : "BOUND"
         }
      ],
      "1991" : [
         {
            "date" : "Jan",
            "issue" : "3",
            "status" : "BOUND"
         },
         {
            "date" : "Apr",
            "issue" : "4",
            "status" : "BOUND"
         },
         {
            "date" : "Jul",
            "issue" : "5",
            "status" : "BOUND"
         },
         {
            "date" : "Oct",
            "issue" : "6",
            "status" : "BOUND"
         }
      ],
      "1992" : [
         {
            "date" : "Jan",
            "issue" : "7",
            "status" : "BOUND"
         },
         {
            "date" : "Apr",
            "issue" : "8",
            "status" : "BOUND"
         },
         {
            "date" : "Jul",
            "issue" : "9",
            "status" : "BOUND"
         },
         {
            "date" : "Oct",
            "issue" : "10",
            "status" : "BOUND"
         }
      ],
      "1993" : [
         {
            "date" : "Apr",
            "issue" : "11",
            "status" : "BOUND"
         },
         {
            "date" : "Oct",
            "issue" : "12",
            "status" : "BOUND"
         }
      ],
      "1994" : [
         {
            "date" : "Apr",
            "issue" : "13",
            "status" : "OWNED"
         },
         {
            "date" : "Oct",
            "issue" : "14",
            "status" : "OWNED"
         }
      ],
      "1995" : [
         {
            "date" : "Apr",
            "issue" : "15",
            "status" : "OWNED"
         },
         {
            "date" : "Oct",
            "issue" : "16",
            "status" : "OWNED"
         }
      ],
      "1996" : [
         {
            "date" : "Apr",
            "issue" : "17",
            "status" : "OWNED"
         },
         {
            "date" : "Oct",
            "issue" : "18",
            "status" : "OWNED"
         }
      ],
      "1997" : [
         {
            "date" : "Oct",
            "issue" : "19",
            "status" : "OWNED"
         }
      ],
      "1998" : [
         {
            "date" : "Apr",
            "issue" : "20/21",
            "status" : "OWNED"
         },
         {
            "date" : "Oct",
            "issue" : "22",
            "status" : "MISSING"
         }
      ],
      "1999" : [
         {
            "date" : "Apr",
            "issue" : "23",
            "status" : "MISSING"
         },
         {
            "date" : "Oct",
            "issue" : "24",
            "status" : "MISSING"
         }
      ],
      "2000" : [
         {
            "date" : "Oct",
            "issue" : "25/26",
            "status" : "MISSING"
         }
      ],
      "2001" : [
         {
            "date" : "Oct",
            "issue" : "27/28",
            "status" : "MISSING"
         }
      ],
      "2002" : [
         {
            "date" : "Apr",
            "issue" : "29",
            "status" : "MISSING"
         },
         {
            "date" : "Oct",
            "issue" : "30",
            "status" : "OWNED"
         }
      ],
      "2003" : [
         {
            "date" : "Oct",
            "issue" : "31",
            "status" : "MISSING"
         }
      ],
      "2004" : [
         {
            "date" : "Apr",
            "issue" : "32",
            "status" : "MISSING"
         },
         {
            "date" : "Oct",
            "issue" : "33/34/35",
            "status" : "MISSING"
         }
      ],
      "2005" : [
         {
            "date" : "Dec",
            "issue" : "36",
            "status" : "MISSING"
         }
      ],
      "2007" : [
         {
            "date" : "Mar",
            "issue" : "37",
            "status" : "MISSING"
         },
         {
            "date" : "Nov",
            "issue" : "38/39",
            "status" : "MISSING"
         }
      ],
      "2008" : [
         {
            "date" : "Apr",
            "issue" : "40",
            "status" : "MISSING"
         },
         {
            "date" : "Dec",
            "issue" : "41",
            "status" : "MISSING"
         }
      ],
      "2009" : [
         {
            "date" : "Aug",
            "issue" : "42",
            "status" : "MISSING"
         }
      ],
      "2010" : [
         {
            "date" : "Jun",
            "issue" : "43",
            "status" : "MISSING"
         },
         {
            "date" : "Sep",
            "issue" : "44",
            "status" : "MISSING"
         }
      ],
      "2011" : [
         {
            "date" : "Oct",
            "issue" : "45",
            "status" : "MISSING"
         },
         {
            "date" : "Nov",
            "issue" : "46",
            "status" : "MISSING"
         }
      ],
      "2012" : [
         {
            "date" : "Feb",
            "issue" : "47",
            "status" : "MISSING"
         },
         {
            "date" : "Mar",
            "issue" : "48",
            "status" : "MISSING"
         },
         {
            "date" : "Apr",
            "issue" : "49",
            "status" : "MISSING"
         },
         {
            "date" : "May",
            "issue" : "50",
            "status" : "MISSING"
         },
         {
            "date" : "Jun",
            "issue" : "51",
            "status" : "MISSING"
         },
         {
            "date" : "Jul",
            "issue" : "52",
            "status" : "MISSING"
         },
         {
            "date" : "Aug",
            "issue" : "53",
            "status" : "MISSING"
         },
         {
            "date" : "Sep",
            "issue" : "54",
            "status" : "MISSING"
         },
         {
            "date" : "Oct",
            "issue" : "55",
            "status" : "MISSING"
         },
         {
            "date" : "Nov",
            "issue" : "56",
            "status" : "MISSING"
         }
      ],
      "2013" : [
         {
            "date" : "Jan",
            "issue" : "57",
            "status" : "MISSING"
         },
         {
            "date" : "Feb",
            "issue" : "58",
            "status" : "MISSING"
         },
         {
            "date" : "Apr",
            "issue" : "59",
            "status" : "MISSING"
         },
         {
            "date" : "May",
            "issue" : "60",
            "status" : "MISSING"
         },
         {
            "date" : "Jun",
            "issue" : "61",
            "status" : "MISSING"
         },
         {
            "date" : "Jul",
            "issue" : "62",
            "status" : "MISSING"
         },
         {
            "date" : "Aug",
            "issue" : "63",
            "status" : "MISSING"
         },
         {
            "date" : "Sep",
            "issue" : "64",
            "status" : "MISSING"
         },
         {
            "date" : "Oct",
            "issue" : "65",
            "status" : "MISSING"
         },
         {
            "date" : "Nov",
            "issue" : "66",
            "status" : "MISSING"
         }
      ],
      "2014" : [
         {
            "date" : "Feb",
            "issue" : "67",
            "status" : "MISSING"
         },
         {
            "date" : "Mar",
            "issue" : "68",
            "status" : "MISSING"
         },
         {
            "date" : "Apr",
            "issue" : "69",
            "status" : "MISSING"
         },
         {
            "date" : "May",
            "issue" : "70",
            "status" : "MISSING"
         },
         {
            "date" : "Jun",
            "issue" : "71",
            "status" : "MISSING"
         },
         {
            "date" : "Jul",
            "issue" : "72",
            "status" : "MISSING"
         },
         {
            "date" : "Aug",
            "issue" : "73",
            "status" : "MISSING"
         },
         {
            "date" : "Sep",
            "issue" : "74",
            "status" : "MISSING"
         },
         {
            "date" : "Oct",
            "issue" : "75",
            "status" : "MISSING"
         },
         {
            "date" : "Nov",
            "issue" : "76",
            "status" : "MISSING"
         }
      ],
      "2015" : [
         {
            "date" : "Feb",
            "issue" : "77",
            "status" : "MISSING"
         },
         {
            "date" : "Mar",
            "issue" : "78",
            "status" : "MISSING"
         },
         {
            "date" : "Apr",
            "issue" : "79",
            "status" : "MISSING"
         },
         {
            "date" : "May",
            "issue" : "80",
            "status" : "MISSING"
         },
         {
            "date" : "Jun",
            "issue" : "81",
            "status" : "MISSING"
         },
         {
            "date" : "Jul",
            "issue" : "82",
            "status" : "MISSING"
         },
         {
            "date" : "Aug",
            "issue" : "83",
            "status" : "MISSING"
         },
         {
            "date" : "Sep",
            "issue" : "84",
            "status" : "MISSING"
         },
         {
            "date" : "Oct",
            "issue" : "85",
            "status" : "MISSING"
         },
         {
            "date" : "Nov",
            "issue" : "86",
            "status" : "MISSING"
         }
      ],
      "2016" : [
         {
            "date" : "Feb",
            "issue" : "87",
            "status" : "MISSING"
         },
         {
            "date" : "Mar",
            "issue" : "88",
            "status" : "MISSING"
         },
         {
            "date" : "Apr",
            "issue" : "89",
            "status" : "MISSING"
         },
         {
            "date" : "May",
            "issue" : "90",
            "status" : "MISSING"
         },
         {
            "date" : "Jun",
            "issue" : "91",
            "status" : "MISSING"
         },
         {
            "date" : "Jul",
            "issue" : "92",
            "status" : "MISSING"
         },
         {
            "date" : "Aug",
            "issue" : "93",
            "status" : "MISSING"
         },
         {
            "date" : "Sep",
            "issue" : "94",
            "status" : "MISSING"
         },
         {
            "date" : "Oct",
            "issue" : "95",
            "status" : "MISSING"
         },
         {
            "date" : "Nov",
            "issue" : "96",
            "status" : "MISSING"
         }
      ],
      "2017" : [
         {
            "date" : "Feb",
            "issue" : "97",
            "status" : "MISSING"
         },
         {
            "date" : "Mar",
            "issue" : "98",
            "status" : "MISSING"
         },
         {
            "date" : "Apr",
            "issue" : "99",
            "status" : "MISSING"
         },
         {
            "date" : "May",
            "issue" : "100",
            "status" : "MISSING"
         },
         {
            "date" : "Jun",
            "issue" : "101",
            "status" : "MISSING"
         },
         {
            "date" : "Jul",
            "issue" : "102",
            "status" : "MISSING"
         },
         {
            "date" : "Aug",
            "issue" : "103",
            "status" : "MISSING"
         },
         {
            "date" : "Sep",
            "issue" : "104",
            "status" : "MISSING"
         },
         {
            "date" : "Oct",
            "issue" : "105",
            "status" : "MISSING"
         },
         {
            "date" : "Nov",
            "issue" : "106",
            "status" : "MISSING"
         }
      ],
      "2018" : [
         {
            "date" : "Feb",
            "issue" : "107",
            "status" : "MISSING"
         },
         {
            "date" : "Mar",
            "issue" : "108",
            "status" : "MISSING"
         },
         {
            "date" : "Apr",
            "issue" : "109",
            "status" : "MISSING"
         },
         {
            "date" : "May",
            "issue" : "110",
            "status" : "MISSING"
         },
         {
            "date" : "Jun",
            "issue" : "111",
            "status" : "MISSING"
         },
         {
            "date" : "Jul",
            "issue" : "112",
            "status" : "MISSING"
         },
         {
            "date" : "Aug",
            "issue" : "113",
            "status" : "MISSING"
         },
         {
            "date" : "Sep",
            "issue" : "114",
            "status" : "MISSING"
         },
         {
            "date" : "Oct",
            "issue" : "115",
            "status" : "MISSING"
         },
         {
            "date" : "Nov",
            "issue" : "116",
            "status" : "MISSING"
         }
      ],
      "2019" : [
         {
            "date" : "Feb",
            "issue" : "117",
            "status" : "MISSING"
         },
         {
            "date" : "Mar",
            "issue" : "118",
            "status" : "MISSING"
         },
         {
            "date" : "Apr",
            "issue" : "119",
            "status" : "MISSING"
         },
         {
            "date" : "May",
            "issue" : "120",
            "status" : "MISSING"
         },
         {
            "date" : "Jun",
            "issue" : "121",
            "status" : "MISSING"
         },
         {
            "date" : "Jul",
            "issue" : "122",
            "status" : "MISSING"
         },
         {
            "date" : "Aug",
            "issue" : "123",
            "status" : "MISSING"
         },
         {
            "date" : "Sep",
            "issue" : "124",
            "status" : "MISSING"
         },
         {
            "date" : "Oct",
            "issue" : "125",
            "status" : "MISSING"
         },
         {
            "date" : "Nov",
            "issue" : "126",
            "status" : "MISSING"
         }
      ],
      "2020" : [
         {
            "date" : "Feb",
            "issue" : "127",
            "status" : "MISSING"
         },
         {
            "date" : "Mar",
            "issue" : "128",
            "status" : "MISSING"
         },
         {
            "date" : "Apr",
            "issue" : "129",
            "status" : "MISSING"
         },
         {
            "date" : "May",
            "issue" : "130",
            "status" : "MISSING"
         },
         {
            "date" : "Jun",
            "issue" : "131",
            "status" : "MISSING"
         },
         {
            "date" : "Jul",
            "issue" : "132",
            "status" : "MISSING"
         },
         {
            "date" : "Aug",
            "issue" : "133",
            "status" : "MISSING"
         },
         {
            "date" : "Sep",
            "issue" : "134",
            "status" : "MISSING"
         },
         {
            "date" : "Oct",
            "issue" : "135",
            "status" : "MISSING"
         },
         {
            "date" : "Nov",
            "issue" : "136",
            "status" : "MISSING"
         }
      ],
      "2021" : [
         {
            "date" : "Feb",
            "issue" : "137",
            "status" : "MISSING"
         },
         {
            "date" : "Mar",
            "issue" : "138",
            "status" : "MISSING"
         },
         {
            "date" : "Apr",
            "issue" : "139",
            "status" : "MISSING"
         },
         {
            "date" : "May",
            "issue" : "140",
            "status" : "MISSING"
         },
         {
            "date" : "Jun",
            "issue" : "141",
            "status" : "MISSING"
         },
         {
            "date" : "Jul",
            "issue" : "142",
            "status" : "MISSING"
         },
         {
            "date" : "Aug",
            "issue" : "143",
            "status" : "MISSING"
         },
         {
            "date" : "Sep",
            "issue" : "144",
            "status" : "MISSING"
         },
         {
            "date" : "Oct",
            "issue" : "145",
            "status" : "MISSING"
         },
         {
            "date" : "Nov",
            "issue" : "146",
            "status" : "MISSING"
         }
      ],
      "2022" : [
         {
            "date" : "Feb",
            "issue" : "147",
            "status" : "MISSING"
         },
         {
            "date" : "Mar",
            "issue" : "148",
            "status" : "MISSING"
         },
         {
            "date" : "Apr",
            "issue" : "149",
            "status" : "MISSING"
         },
         {
            "date" : "May",
            "issue" : "150",
            "status" : "MISSING"
         },
         {
            "date" : "Jun",
            "issue" : "151",
            "status" : "MISSING"
         },
         {
            "date" : "Jul",
            "issue" : "152",
            "status" : "MISSING"
         },
         {
            "date" : "Aug",
            "issue" : "153",
            "status" : "MISSING"
         },
         {
            "date" : "Sep",
            "issue" : "154",
            "status" : "MISSING"
         },
         {
            "date" : "Oct",
            "issue" : "155",
            "status" : "MISSING"
         },
         {
            "date" : "Nov",
            "issue" : "156",
            "status" : "MISSING"
         }
      ],
      "2023" : [
         {
            "date" : "Feb",
            "issue" : "157",
            "status" : "MISSING"
         },
         {
            "date" : "Mar",
            "issue" : "158",
            "status" : "MISSING"
         },
         {
            "date" : "Apr",
            "issue" : "159",
            "status" : "MISSING"
         },
         {
            "date" : "May",
            "issue" : "160",
            "status" : "MISSING"
         },
         {
            "date" : "Jun",
            "issue" : "161",
            "status" : "MISSING"
         },
         {
            "date" : "Jul",
            "issue" : "162",
            "status" : "MISSING"
         },
         {
            "date" : "Aug",
            "issue" : "163",
            "status" : "MISSING"
         },
         {
            "date" : "Sep",
            "issue" : "164",
            "status" : "MISSING"
         },
         {
            "date" : "Oct",
            "issue" : "165",
            "status" : "MISSING"
         },
         {
            "date" : "Nov",
            "issue" : "166",
            "status" : "MISSING"
         }
      ],
      "2024" : [
         {
            "date" : "Feb",
            "issue" : "167",
            "status" : "MISSING"
         },
         {
            "date" : "Mar",
            "issue" : "168",
            "status" : "MISSING"
         },
         {
            "date" : "Apr",
            "issue" : "169",
            "status" : "MISSING"
         },
         {
            "date" : "May",
            "issue" : "170",
            "status" : "MISSING"
         },
         {
            "date" : "Jun",
            "issue" : "171",
            "status" : "MISSING"
         },
         {
            "date" : "Jul",
            "issue" : "172",
            "status" : "MISSING"
         },
         {
            "date" : "Aug",
            "issue" : "173",
            "status" : "MISSING"
         },
         {
            "date" : "Sep",
            "issue" : "174",
            "status" : "MISSING"
         },
         {
            "date" : "Oct",
            "issue" : "175",
            "status" : "MISSING"
         },
         {
            "date" : "Nov",
            "issue" : "176",
            "status" : "MISSING"
         }
      ]
   }
}
